README.md
setup.py
common_utilities/__init__.py
common_utilities/convert.py
common_utilities/dateutils.py
common_utilities/settler.py
common_utilities.egg-info/PKG-INFO
common_utilities.egg-info/SOURCES.txt
common_utilities.egg-info/dependency_links.txt
common_utilities.egg-info/not-zip-safe
common_utilities.egg-info/top_level.txt