Metadata-Version: 2.1
Name: common-utilities
Version: 0.0.8
Summary: Common utilities
Home-page: UNKNOWN
Author: hacfox
Author-email: zz.hacfox@gmail.com
License: UNKNOWN
Platform: UNKNOWN
Classifier: Programming Language :: Python :: 3.6
